[{
    "j_no":2,
    "name":"Asiana Times",
    "position":"Graphic Design Intern",
    "time_period":"Nov 2022 - Dec 2022",
    "description":[
        "Created posters and illustrations for news articles.",
        "Managed the same on social media handles."
    ]
},

{   "j_no":1,
    "name":"Google Developer Student Clubs- Galgotias University",
    "position":"Graphic Design Lead",
    "time_period":"Sep 2022 - Aug 2023",
    "description":[
        "Created posters for various events online using canva.",
        "Created illustrations and slides for various teaching sessions hosted by club members using Adobe Illustrator",
        "Created templates for social handles.",
        "Gained experience in working within a team environment and effective communication"

    ]
}]




